magic_motion_metrics/__init__.py
magic_motion_metrics-0.1.dist-info/METADATA
magic_motion_metrics-0.1.dist-info/WHEEL
magic_motion_metrics-0.1.dist-info/top_level.txt
magic_motion_metrics-0.1.dist-info/RECORD
