Metadata-Version: 2.1
Name: magic-motion-metrics
Version: 0.1
Summary: This package calculate metrics data using bvh motion data of a human
Author: Muhammad Tariq 
Author-email: tariq@movrs.com
